finops/__init__.py
finops/codal.py
finops/config.py
finops/logger.py
finops/tehran_stock_exchange.py
finops/ticker.py
finops/utils/__init__.py
finops/utils/downloader.py
finops/utils/preprocessor.py
finops/utils/scraper.py
finops/utils/wrappers.py
tests/__init__.py
tests/test_tehran_stock_exchange.py
tests/test_ticker.py
tests/test_utils/__init__.py
tests/test_utils/test_downloader.py
tests/test_utils/test_scraper.py
finops-0.2.8.dist-info/LICENSE
finops-0.2.8.dist-info/METADATA
finops-0.2.8.dist-info/WHEEL
finops-0.2.8.dist-info/top_level.txt
finops-0.2.8.dist-info/RECORD
