Metadata-Version: 2.1
Name: finops
Version: 0.2.8
Summary: A Python package for financial operations.
Home-page: https://github.com/nixuri/FinOps
Author: Alireza Nilgaran
Author-email: alireza.nilgaran@gmail.com
License: BSD (3-clause)
Classifier: Development Status :: 4 - Beta
Classifier: Intended Audience :: Financial and Insurance Industry
Classifier: License :: OSI Approved :: BSD License
Classifier: Programming Language :: Python :: 3
Requires-Python: >=3.6
License-File: LICENSE
Requires-Dist: numpy
Requires-Dist: pandas
Requires-Dist: requests
Requires-Dist: beautifulsoup4
Requires-Dist: datetime
Requires-Dist: jdatetime
Requires-Dist: selenium
